roodmus/__init__.py
roodmus/bibtex.py
roodmus/ccpem_logo.png
roodmus/constants.py
roodmus/protocols.conf
roodmus/protocols/__init__.py
roodmus/protocols/protocol_simulate_micrographs.py
roodmus/tests/__init__.py
roodmus/tests/test_roodmus.py
roodmus/viewers/__init__.py
roodmus/wizards/__init__.py
scipion_em_roodmus-1.0.4.dist-info/LICENSE
scipion_em_roodmus-1.0.4.dist-info/METADATA
scipion_em_roodmus-1.0.4.dist-info/WHEEL
scipion_em_roodmus-1.0.4.dist-info/entry_points.txt
scipion_em_roodmus-1.0.4.dist-info/top_level.txt
scipion_em_roodmus-1.0.4.dist-info/RECORD
