Metadata-Version: 2.1
Name: scipion-em-roodmus
Version: 1.0.4
Summary: Roodmus plugin for Scipion
Home-page: https://github.com/scipion-em/scipion-em-roodmus
Author: David Herreros
Author-email: dherreros@cnb.csic.es
Project-URL: Bug Reports, https://github.com/scipion-em/scipion-em-roodmus/issues
Project-URL: Source, https://github.com/scipion-em/scipion-em-roodmus/
Keywords: scipion cryoem imageprocessing scipion-3.0 datasimulation
License-File: LICENSE
Requires-Dist: scipion-pyworkflow
Requires-Dist: scipion-em
Requires-Dist: pyyaml
